gtdbtk/__init__.py
gtdbtk/__main__.py
gtdbtk/ani_rep.py
gtdbtk/ani_screen.py
gtdbtk/classify.py
gtdbtk/cli.py
gtdbtk/decorate.py
gtdbtk/exceptions.py
gtdbtk/infer_ranks.py
gtdbtk/main.py
gtdbtk/markers.py
gtdbtk/misc.py
gtdbtk/relative_distance.py
gtdbtk/reroot_tree.py
gtdbtk/split.py
gtdbtk/tools.py
gtdbtk/trim_msa.py
gtdbtk/biolib_lite/__init__.py
gtdbtk/biolib_lite/common.py
gtdbtk/biolib_lite/custom_help_formatter.py
gtdbtk/biolib_lite/exceptions.py
gtdbtk/biolib_lite/execute.py
gtdbtk/biolib_lite/logger.py
gtdbtk/biolib_lite/newick.py
gtdbtk/biolib_lite/parallel.py
gtdbtk/biolib_lite/prodigal_biolib.py
gtdbtk/biolib_lite/seq_io.py
gtdbtk/biolib_lite/taxonomy.py
gtdbtk/config/__init__.py
gtdbtk/config/common.py
gtdbtk/config/output.py
gtdbtk/external/__init__.py
gtdbtk/external/fastani.py
gtdbtk/external/fasttree.py
gtdbtk/external/hmm_aligner.py
gtdbtk/external/pfam_search.py
gtdbtk/external/pplacer.py
gtdbtk/external/prodigal.py
gtdbtk/external/skani.py
gtdbtk/external/tigrfam_search.py
gtdbtk/external/pypfam/__init__.py
gtdbtk/external/pypfam/HMM/HMMMatch.py
gtdbtk/external/pypfam/HMM/HMMResults.py
gtdbtk/external/pypfam/HMM/HMMResultsIO.py
gtdbtk/external/pypfam/HMM/HMMSequence.py
gtdbtk/external/pypfam/HMM/HMMUnit.py
gtdbtk/external/pypfam/HMM/__init__.py
gtdbtk/external/pypfam/Scan/PfamScan.py
gtdbtk/external/pypfam/Scan/__init__.py
gtdbtk/files/__init__.py
gtdbtk/files/batchfile.py
gtdbtk/files/classify_summary.py
gtdbtk/files/gtdb_radii.py
gtdbtk/files/marker_info.py
gtdbtk/files/missing_genomes.py
gtdbtk/files/pplacer_classification.py
gtdbtk/files/red_dict.py
gtdbtk/files/stage_logger.py
gtdbtk/files/tree_mapping.py
gtdbtk/files/marker/__init__.py
gtdbtk/files/marker/copy_number.py
gtdbtk/files/marker/tophit.py
gtdbtk/files/prodigal/__init__.py
gtdbtk/files/prodigal/tln_table.py
gtdbtk/files/prodigal/tln_table_summary.py
gtdbtk/model/__init__.py
gtdbtk/model/enum.py
gtdbtk/pipeline/__init__.py
gtdbtk/pipeline/align.py
gtdbtk/pipeline/export_msa.py
gtdbtk-2.6.1.dist-info/LICENSE
gtdbtk-2.6.1.dist-info/METADATA
gtdbtk-2.6.1.dist-info/WHEEL
gtdbtk-2.6.1.dist-info/entry_points.txt
gtdbtk-2.6.1.dist-info/top_level.txt
gtdbtk-2.6.1.dist-info/RECORD
