Metadata-Version: 2.1
Name: gtdbtk
Version: 2.6.1
Summary: A toolkit for assigning objective taxonomic classifications to bacterial and archaeal genomes.
Home-page: https://github.com/Ecogenomics/GTDBTk
Author: Pierre-Alain Chaumeil, Aaron Mussig and Donovan Parks
Author-email: p.chaumeil@uq.edu.au
Maintainer: Pierre-Alain Chaumeil, Aaron Mussig and Donovan Parks
Maintainer-email: donovan.parks@gmail.com
License: GPL3
Classifier: Development Status :: 5 - Production/Stable
Classifier: Intended Audience :: Science/Research
Classifier: License :: OSI Approved :: GNU General Public License v3 (GPLv3)
Classifier: Natural Language :: English
Classifier: Programming Language :: Python :: 3
Classifier: Programming Language :: Python :: 3.6
Classifier: Programming Language :: Python :: 3.7
Classifier: Programming Language :: Python :: 3.8
Classifier: Topic :: Scientific/Engineering :: Bio-Informatics
Requires-Python: >=3.6
License-File: LICENSE
Requires-Dist: dendropy~=4.1
Requires-Dist: numpy~=1.9
Requires-Dist: tqdm~=4.35
Requires-Dist: pydantic~=1.9
